ndice/__init__.py
ndice/constants.py
ndice/dice.py
ndice/interned.py
ndice/mods.py
ndice/op.py
ndice/py.typed
ndice/rng.py
ndice/roll.py
ndice-0.1.10.dist-info/licenses/LICENSE
ndice-0.1.10.dist-info/WHEEL
ndice-0.1.10.dist-info/METADATA
ndice-0.1.10.dist-info/RECORD
