Metadata-Version: 2.4
Name: ndice
Version: 0.1.10
Summary: A dice rolling library for games.
Keywords: dice,roll,random,game,rpg
Author: Don McCaughey
Author-email: Don McCaughey <don@donm.cc>
License-Expression: BSD-2-Clause
License-File: LICENSE
Classifier: Development Status :: 3 - Alpha
Classifier: Intended Audience :: Developers
Classifier: License :: OSI Approved :: BSD License
Classifier: Operating System :: OS Independent
Classifier: Programming Language :: Python :: 3.13
Classifier: Topic :: Games/Entertainment :: Role-Playing
Requires-Python: >=3.13
Project-URL: Changelog, https://git.sr.ht/~donmcc/ndice/tree/main/item/CHANGELOG.md
Project-URL: Documentation, https://ndice.donm.cc
Project-URL: Homepage, https://git.sr.ht/~donmcc/ndice
Project-URL: Repository, https://git.sr.ht/~donmcc/ndice
